sqlcheck/__init__.py
sqlcheck/__main__.py
sqlcheck/discovery.py
sqlcheck/execution.py
sqlcheck/function_context.py
sqlcheck/function_registry.py
sqlcheck/models.py
sqlcheck/parser.py
sqlcheck/plugins.py
sqlcheck/reports.py
sqlcheck/runner.py
sqlcheck/template.py
sqlcheck/version.py
sqlcheck/cli/__init__.py
sqlcheck/cli/app.py
sqlcheck/cli/common.py
sqlcheck/cli/discovery.py
sqlcheck/cli/main.py
sqlcheck/cli/output.py
sqlcheck/cli/commands/__init__.py
sqlcheck/cli/commands/parse.py
sqlcheck/cli/commands/plan.py
sqlcheck/cli/commands/run.py
sqlcheck/db/__init__.py
sqlcheck/db/connection.py
sqlcheck/db/constants.py
sqlcheck/db/engine.py
sqlcheck/db/exceptions.py
sqlcheck/db/models.py
sqlcheck/db/resolver.py
sqlcheck/functions/__init__.py
sqlcheck/functions/assess.py
sqlcheck/functions/fail.py
sqlcheck/functions/success.py
pysqlcheck-0.0.3.dist-info/METADATA
pysqlcheck-0.0.3.dist-info/WHEEL
pysqlcheck-0.0.3.dist-info/entry_points.txt
pysqlcheck-0.0.3.dist-info/RECORD
