Metadata-Version: 2.4
Name: pysqlcheck
Version: 0.0.3
Summary: CLI for SQL test validation
Project-URL: Repository, https://github.com/luisggc/sqlcheck
Author: Luis Coimbra
License: MIT
Classifier: Development Status :: 3 - Alpha
Classifier: Intended Audience :: Developers
Classifier: License :: OSI Approved :: MIT License
Classifier: Programming Language :: Python :: 3
Classifier: Programming Language :: Python :: 3.10
Classifier: Programming Language :: Python :: 3.11
Classifier: Programming Language :: Python :: 3.12
Requires-Python: >=3.11
Requires-Dist: common-expression-language>=0.5.3
Requires-Dist: jinja2>=3.1.0
Requires-Dist: pyyaml>=6.0.3
Requires-Dist: rich>=14.2.0
Requires-Dist: sqlalchemy>=2.0.0
Requires-Dist: typer>=0.21.0
Provides-Extra: all
Requires-Dist: databricks-sql-connector>=3.0.0; extra == 'all'
Requires-Dist: duckdb-engine>=0.10.0; extra == 'all'
Requires-Dist: duckdb>=1.0.0; extra == 'all'
Requires-Dist: oracledb>=2.0.0; extra == 'all'
Requires-Dist: psycopg[binary]>=3.1.0; extra == 'all'
Requires-Dist: pymysql>=1.0.0; extra == 'all'
Requires-Dist: pyodbc>=5.0.0; extra == 'all'
Requires-Dist: snowflake-sqlalchemy>=1.5.0; extra == 'all'
Provides-Extra: databricks
Requires-Dist: databricks-sql-connector>=3.0.0; extra == 'databricks'
Provides-Extra: dev
Requires-Dist: pytest>=8.0.0; extra == 'dev'
Provides-Extra: duckdb
Requires-Dist: duckdb-engine>=0.10.0; extra == 'duckdb'
Requires-Dist: duckdb>=1.0.0; extra == 'duckdb'
Provides-Extra: mssql
Requires-Dist: pyodbc>=5.0.0; extra == 'mssql'
Provides-Extra: mysql
Requires-Dist: pymysql>=1.0.0; extra == 'mysql'
Provides-Extra: oracle
Requires-Dist: oracledb>=2.0.0; extra == 'oracle'
Provides-Extra: postgres
Requires-Dist: psycopg[binary]>=3.1.0; extra == 'postgres'
Provides-Extra: snowflake
Requires-Dist: snowflake-sqlalchemy>=1.5.0; extra == 'snowflake'
